wordhuntanagram/__init__.py
wordhuntanagram/anagram.py
wordhuntanagram/base.py
wordhuntanagram/file_tree.py
wordhuntanagram/logger.py
wordhuntanagram/matrices.py
wordhuntanagram/wordhunt.py
wordhuntanagram/words.json
wordhuntanagram/data/trie_store.json
wordhunt_anagram_search_python-0.1.2.dist-info/LICENSE
wordhunt_anagram_search_python-0.1.2.dist-info/METADATA
wordhunt_anagram_search_python-0.1.2.dist-info/WHEEL
wordhunt_anagram_search_python-0.1.2.dist-info/top_level.txt
wordhunt_anagram_search_python-0.1.2.dist-info/RECORD
