Metadata-Version: 2.1
Name: wordhunt-anagram-search-python
Version: 0.1.2
Summary: A python client library for word search in games like iMessage wordhunt and anagram.
Home-page: https://github.com/bstudiosoriginal/WordHuntAnagram
Author: Immanuel Adotey Allotey
Author-email: imma.adt@gmail.com
License: UNKNOWN
Keywords: word games,word search,anagram,wordhunt,iMessage games
Platform: UNKNOWN
Classifier: Development Status :: 3 - Alpha
Classifier: Intended Audience :: End Users/Desktop
Classifier: License :: OSI Approved :: MIT License
Classifier: Natural Language :: English
Classifier: Operating System :: OS Independent
Classifier: Programming Language :: Python :: 3 :: Only
Classifier: Programming Language :: Python :: 3.5
Classifier: Programming Language :: Python :: 3.6
Classifier: Programming Language :: Python :: 3.7
Classifier: Programming Language :: Python :: 3.8
Classifier: Programming Language :: Python :: 3.9
Requires-Python: >=3.5
